QRePS/__init__.py
QRePS/stattest_metrics.py
QRePS-1.2.1.dist-info/METADATA
QRePS-1.2.1.dist-info/WHEEL
QRePS-1.2.1.dist-info/entry_points.txt
QRePS-1.2.1.dist-info/top_level.txt
QRePS-1.2.1.dist-info/RECORD
