Metadata-Version: 2.1
Name: QRePS
Version: 1.2.1
Summary: A utility for statistical comparison of protein identification results in proteomics and calculation of quantitative metrics for total cellular response
Author: Elizaveta Kazakova
Author-email: kazakova.em@phystech.edu
License: License :: OSI Approved :: Apache Software License
Classifier: Intended Audience :: Science/Research
Classifier: Programming Language :: Python :: 3
Classifier: Topic :: Scientific/Engineering :: Bio-Informatics
Classifier: Topic :: Scientific/Engineering :: Chemistry
Classifier: Topic :: Scientific/Engineering :: Physics
Requires-Dist: numpy
Requires-Dist: pandas
Requires-Dist: statsmodels
Requires-Dist: scipy
Requires-Dist: matplotlib
Requires-Dist: seaborn
Requires-Dist: scikit-learn
Requires-Dist: requests
Requires-Dist: matplotlib-inline
Requires-Dist: IPython
